erlanglib/__init__.py
erlanglib/core.py
erlanglib-1.2.0.dist-info/LICENSE
erlanglib-1.2.0.dist-info/METADATA
erlanglib-1.2.0.dist-info/WHEEL
erlanglib-1.2.0.dist-info/top_level.txt
erlanglib-1.2.0.dist-info/RECORD
