Metadata-Version: 2.1
Name: erlanglib
Version: 1.2.0
Summary: A simple library for Erlang calculations
Home-page: https://github.com/TechyGuy2000/erlanglib
Author: Greg Bolton
Author-email: greg.bolton.28@gmail.com
License: MIT
Classifier: Programming Language :: Python :: 3
Classifier: License :: OSI Approved :: MIT License
Classifier: Operating System :: OS Independent
Requires-Python: >=3.6
License-File: LICENSE
